README.md
setup.py
invana_transformers.egg-info/PKG-INFO
invana_transformers.egg-info/SOURCES.txt
invana_transformers.egg-info/dependency_links.txt
invana_transformers.egg-info/requires.txt
invana_transformers.egg-info/top_level.txt
tests/__init__.py
tests/test_json_bender.py
tests/test_output_bender.py
tests/test_output_renderer.py
tests/test_read_from_file.py
tests/test_read_from_mongodb.py
transformers/__init__.py
transformers/executors.py
transformers/fields.py
transformers/managers.py
transformers/renderers.py
transformers/transforms.py
transformers/utils.py