Metadata-Version: 1.0
Name: invana-transformers
Version: 0.0.0b0
Summary: A library to transforming JSON with parsers.
Home-page: https://github.com/invanalabs/data-transformers
Author: Ravi RT Merugu
Author-email: ravi@invanalabs.ai
License: MIT
Platform: UNKNOWN
